{
  "name": "Jack Russell",
  "age": 45,
  "address": {
    "street": "Tiza Parkway",
    "city": "Carripdif",
    "state": "MT",
    "zip": "04707"
  },
  "contact": {
    "phone": "(701) 709-8062",
    "servicePhone": "800964118"
  },
  "birthday": "1997-07-23T05:03:30.481Z",
  "ip": "20.54.227.1",
  "foo": "bar",
  "profile": {
    "about": "Dav fuovzu si jik pejpej vod tinjuhac aputober gonpim ipeli esieb kafobcud oku. Fubwuf mibwo luvu fefkinba pismik ile ber ev daw miug zode ijvumtut tavueb vajohfud ip ducoz ep. He wisbuz macuzan ocece apuj tilbe lago vu em usomokpi ogekaf livor. Cohozoku za en igo tohzasif loldavap oh aretis luf wefpohlu gug kacamih nu efsoinu emhe cisow ro gugik.",
    "bio": "Osuka didac ihiojicuw gahnucgur polo dekseze cefnun ra tat lamib kip adicovu nomepvaw woben gilub gotoko nufgo zosadtuh. Hionoud ci huh owtul feas uwu ujavi lije agsesmo tapil met zitsuwdep sowsi. Abise suafato esododma rasawiw ate givbif rew tigonon icwip uzhebo ugipacu ulso botiod efvib ar han wouni. Ruw kikvodke temguva le taw bufip ajizjo itsow laciwso gip ow gez ilposte."
  },
  "apiKey": "3c192388c5f55ab18fd647db3c4eaef6235be7a69059599bf46b6959cb622a3c",
  "currency": {
    "code": "YER",
    "name": "Yemen Rial"
  }
}