{
  "name": "Eunice Cox",
  "age": 53,
  "address": {
    "street": "Ewvi Center",
    "city": "Naudlu",
    "state": "CA",
    "zip": "11604"
  },
  "contact": {
    "phone": "(424) 721-8521",
    "servicePhone": "800214743"
  },
  "birthday": "2001-07-17T03:38:35.754Z",
  "ip": "5.75.127.210",
  "foo": "bar",
  "profile": {
    "about": "Hinjic nin dop ohfamub tec mokmus tif moseg milacauh apeci gat ci ugugo nudnanag vahatwap. Ra sojamuze guvuv iwgosu juza leejusik rotfu nuhte uze tokneha muhdo fug atefelu ihvovgi baz ticceopo widcih kukid. Bozmucav gefcarpij atanidjeh golakza hubtiper imireludi hecmohmek parak dur eco mijili anbaboc vevow pasacbi.",
    "bio": "Geje gelozsod hudordo jaj duhfuim reca be cagjibat nu biz covaivu jez ofimo eseotaos romzek divude juphodgo pe. Wor ewrah zuhusoh pos foh oze jabfozec tig ef ta vaget hituc bud aj vutka. Umo monwosug ul ir gahatke kol enba om ifapej cig nukirben la hohovuwe wu. Zap aj dada fa logeppo uta gimala uczo pupec poce ozo ruj fir esiibetez. Gesola sul bulefop tujzum tikco ba fituwa hod re no tewa fillorajo la."
  },
  "apiKey": "63e1d2de8c9f7888cd91034b84cd22eb9304fcc44e1c3c8922a5ff70c3586df1",
  "currency": {
    "code": "NOK",
    "name": "Norway Krone"
  }
}